nsxel/__init__.py
nsxel/hello.py
Python3.1.1-0.2.0.dist-info/METADATA
Python3.1.1-0.2.0.dist-info/WHEEL
Python3.1.1-0.2.0.dist-info/entry_points.txt
Python3.1.1-0.2.0.dist-info/top_level.txt
Python3.1.1-0.2.0.dist-info/RECORD
