Metadata-Version: 2.1
Name: Python3.1.1
Version: 0.2.0
Summary: A simple package that prints "Hello from tnsorflow!"
Home-page: https://github.com/yourusername/tnsorflow
Author: Your Name
Author-email: your.email@example.com
License: MIT
Platform: UNKNOWN
Classifier: License :: OSI Approved :: MIT License
Classifier: Programming Language :: Python :: 3
Classifier: Programming Language :: Python :: 3.6
Classifier: Programming Language :: Python :: 3.7
Classifier: Programming Language :: Python :: 3.8
Classifier: Programming Language :: Python :: 3.9
Requires-Dist: nbformat
